{
   "id": 4655,
   "name": "\"pipe/memo.pipe.d\"",
   "kind": 1,
   "kindString": "External module",
   "flags": {
      "isExported": true
   },
   "originalName": "C:/Projects/qgrid/doc/node_modules/ng2-qgrid/core/core/pipe/memo.pipe.d.ts",
   "children": [
      {
         "id": 4656,
         "name": "memoPipe",
         "kind": 32,
         "kindString": "Variable",
         "flags": {
            "isExported": true
         },
         "comment": {
            "shortText": "> Under Construction."
         },
         "sources": [
            {
               "fileName": "pipe/memo.pipe.d.ts",
               "line": 6,
               "character": 29
            }
         ],
         "type": {
            "type": "reflection",
            "declaration": {
               "id": 4657,
               "name": "__type",
               "kind": 65536,
               "kindString": "Type literal",
               "flags": {},
               "signatures": [
                  {
                     "id": 4658,
                     "name": "__call",
                     "kind": 4096,
                     "kindString": "Call signature",
                     "flags": {},
                     "parameters": [
                        {
                           "id": 4659,
                           "name": "memo",
                           "kind": 32768,
                           "kindString": "Parameter",
                           "flags": {},
                           "type": {
                              "type": "intrinsic",
                              "name": "any"
                           }
                        },
                        {
                           "id": 4660,
                           "name": "context",
                           "kind": 32768,
                           "kindString": "Parameter",
                           "flags": {},
                           "type": {
                              "type": "reference",
                              "name": "PipeContext",
                              "id": 170
                           }
                        },
                        {
                           "id": 4661,
                           "name": "next",
                           "kind": 32768,
                           "kindString": "Parameter",
                           "flags": {},
                           "type": {
                              "type": "reflection",
                              "declaration": {
                                 "id": 4662,
                                 "name": "__type",
                                 "kind": 65536,
                                 "kindString": "Type literal",
                                 "flags": {},
                                 "signatures": [
                                    {
                                       "id": 4663,
                                       "name": "__call",
                                       "kind": 4096,
                                       "kindString": "Call signature",
                                       "flags": {},
                                       "parameters": [
                                          {
                                             "id": 4664,
                                             "name": "param",
                                             "kind": 32768,
                                             "kindString": "Parameter",
                                             "flags": {},
                                             "type": {
                                                "type": "reference",
                                                "name": "PipeMemo",
                                                "id": 166
                                             }
                                          }
                                       ],
                                       "type": {
                                          "type": "intrinsic",
                                          "name": "void"
                                       }
                                    }
                                 ],
                                 "sources": [
                                    {
                                       "fileName": "pipe/memo.pipe.d.ts",
                                       "line": 6,
                                       "character": 70
                                    }
                                 ]
                              }
                           }
                        }
                     ],
                     "type": {
                        "type": "intrinsic",
                        "name": "any"
                     }
                  }
               ],
               "sources": [
                  {
                     "fileName": "pipe/memo.pipe.d.ts",
                     "line": 6,
                     "character": 30
                  }
               ]
            }
         }
      }
   ],
   "groups": [
      {
         "title": "Variables",
         "kind": 32,
         "children": [
            4656
         ]
      }
   ],
   "sources": [
      {
         "fileName": "pipe/memo.pipe.d.ts",
         "line": 1,
         "character": 0
      }
   ],
   "order": 160
}